trabConfig-0.1.5.dist-info/DESCRIPTION.rst
trabConfig-0.1.5.dist-info/METADATA
trabConfig-0.1.5.dist-info/RECORD
trabConfig-0.1.5.dist-info/WHEEL
trabConfig-0.1.5.dist-info/metadata.json
trabConfig-0.1.5.dist-info/top_level.txt
trabconfig/__init__.py
trabconfig/main.py
