Metadata-Version: 2.0
Name: trabConfig
Version: 0.1.5
Summary: A simple config parser that supports JSON and YAML
Home-page: UNKNOWN
Author: Scott Doucet
Author-email: duroktar@gmail.com
License: MIT
Platform: UNKNOWN
Requires-Dist: pyyaml
